[
    {
        "key": "dbln",
        "value": "%7B%2261551568299522%22%3A%22H2mboqJA%22%2C%2261559695820593%22%3A%22qCtz3MfG%22%7D",
        "domain": "facebook.com",
        "path": "/login/device-based/",
        "hostOnly": false,
        "creation": "2024-08-15T10:42:56.020Z",
        "lastAccessed": "2024-08-15T10:42:56.020Z"
    },
    {
        "key": "datr",
        "value": "uCa4ZhGo41fqSp1PCbToE3xm",
        "domain": "facebook.com",
        "path": "/",
        "hostOnly": false,
        "creation": "2024-08-15T10:42:56.020Z",
        "lastAccessed": "2024-08-15T10:42:56.020Z"
    },
    {
        "key": "sb",
        "value": "uCa4ZvuFB9k1EWUYRhXU9uSR",
        "domain": "facebook.com",
        "path": "/",
        "hostOnly": false,
        "creation": "2024-08-15T10:42:56.020Z",
        "lastAccessed": "2024-08-15T10:42:56.020Z"
    },
    {
        "key": "ps_l",
        "value": "1",
        "domain": "facebook.com",
        "path": "/",
        "hostOnly": false,
        "creation": "2024-08-15T10:42:56.020Z",
        "lastAccessed": "2024-08-15T10:42:56.020Z"
    },
    {
        "key": "ps_n",
        "value": "1",
        "domain": "facebook.com",
        "path": "/",
        "hostOnly": false,
        "creation": "2024-08-15T10:42:56.020Z",
        "lastAccessed": "2024-08-15T10:42:56.020Z"
    },
    {
        "key": "vpd",
        "value": "v1%3B803x412x1.75",
        "domain": "facebook.com",
        "path": "/",
        "hostOnly": false,
        "creation": "2024-08-15T10:42:56.020Z",
        "lastAccessed": "2024-08-15T10:42:56.020Z"
    },
    {
        "key": "dpr",
        "value": "1.75",
        "domain": "facebook.com",
        "path": "/",
        "hostOnly": false,
        "creation": "2024-08-15T10:42:56.020Z",
        "lastAccessed": "2024-08-15T10:42:56.020Z"
    },
    {
        "key": "c_user",
        "value": "61559695820593",
        "domain": "facebook.com",
        "path": "/",
        "hostOnly": false,
        "creation": "2024-08-15T10:42:56.020Z",
        "lastAccessed": "2024-08-15T10:42:56.020Z"
    },
    {
        "key": "fr",
        "value": "0YKmd1lvnvvH86eRP.AWXrmQPVGLfXr9KtuXh8UrAl6eI.BmuCa4..AAA.0.0.BmvDfP.AWWT0N1vhj4",
        "domain": "facebook.com",
        "path": "/",
        "hostOnly": false,
        "creation": "2024-08-15T10:42:56.020Z",
        "lastAccessed": "2024-08-15T10:42:56.020Z"
    },
    {
        "key": "xs",
        "value": "39%3Ai_vzVn3viP-dhg%3A2%3A1723611088%3A-1%3A5132",
        "domain": "facebook.com",
        "path": "/",
        "hostOnly": false,
        "creation": "2024-08-15T10:42:56.020Z",
        "lastAccessed": "2024-08-15T10:42:56.020Z"
    },
    {
        "key": "locale",
        "value": "en_US",
        "domain": "facebook.com",
        "path": "/",
        "hostOnly": false,
        "creation": "2024-08-15T10:42:56.020Z",
        "lastAccessed": "2024-08-15T10:42:56.020Z"
    },
    {
        "key": "m_page_voice",
        "value": "61559695820593",
        "domain": "facebook.com",
        "path": "/",
        "hostOnly": false,
        "creation": "2024-08-15T10:42:56.020Z",
        "lastAccessed": "2024-08-15T10:42:56.020Z"
    },
    {
        "key": "wd",
        "value": "412x803",
        "domain": "facebook.com",
        "path": "/",
        "hostOnly": false,
        "creation": "2024-08-15T10:42:56.020Z",
        "lastAccessed": "2024-08-15T10:42:56.020Z"
    },
    {
        "key": "wl_cbv",
        "value": "v2%3Bclient_version%3A2591%3Btimestamp%3A1723718545",
        "domain": "facebook.com",
        "path": "/",
        "hostOnly": false,
        "creation": "2024-08-15T10:42:56.020Z",
        "lastAccessed": "2024-08-15T10:42:56.020Z"
    },
    {
        "key": "fbl_st",
        "value": "100422475%3BT%3A28728642",
        "domain": "facebook.com",
        "path": "/",
        "hostOnly": false,
        "creation": "2024-08-15T10:42:56.020Z",
        "lastAccessed": "2024-08-15T10:42:56.020Z"
    }
]
